CHANGELOG.rst
LICENSE.txt
MANIFEST.in
README.rst
TODO.txt
VERSION.txt
setup.cfg
setup.py
pdns/__init__.py
pdns/cli.py
pdns/engine.py
pdns/i18n.py
pdns/protocol.py
pdns.egg-info/PKG-INFO
pdns.egg-info/SOURCES.txt
pdns.egg-info/dependency_links.txt
pdns.egg-info/entry_points.txt
pdns.egg-info/requires.txt
pdns.egg-info/top_level.txt
pdns.egg-info/zip-safe