Metadata-Version: 1.1
Name: pdns
Version: 0.1.3
Summary: Command line client to synchronize PowerDNS hosted zones with local zone files
Home-page: http://github.com/metagriffin/pdns
Author: metagriffin
Author-email: mg.pypi@metagriffin.net
License: GPLv3+
Keywords: powerdns api dns zone client command line cli
Platform: any
Classifier: Development Status :: 3 - Alpha
Classifier: Environment :: Console
Classifier: Intended Audience :: System Administrators
Classifier: Programming Language :: Python
Classifier: Operating System :: OS Independent
Classifier: Natural Language :: English
Classifier: License :: OSI Approved :: GNU General Public License v3 or later (GPLv3+)
